atomic_lru/__init__.py
atomic_lru/_cache.py
atomic_lru/py.typed
atomic_lru/_storage/__init__.py
atomic_lru/_storage/storage.py
atomic_lru/_storage/thread.py
atomic_lru/_storage/types.py
atomic_lru/_storage/value.py
atomic_lru-0.0.3.dist-info/licenses/LICENSE
atomic_lru-0.0.3.dist-info/METADATA
atomic_lru-0.0.3.dist-info/WHEEL
atomic_lru-0.0.3.dist-info/top_level.txt
atomic_lru-0.0.3.dist-info/RECORD
