Metadata-Version: 2.4
Name: atomic-lru
Version: 0.0.3
Summary: Thread-safe, dependency-free in-memory LRU storage library for Python 3.12+ (with optional TTL)
Author-email: Fabien MARTY <fabien.marty@gmail.com>
Maintainer-email: Fabien MARTY <fab@fabien-marty.dev>
License-Expression: MIT
Project-URL: Homepage, https://github.com/fabien-marty/atomic-lru
Project-URL: Repository, https://github.com/fabien-marty/atomic-lru.git
Requires-Python: >=3.12
License-File: LICENSE
Dynamic: license-file
